<!DOCTYPE suite SYSTEM "http://testng.org/testng-1.0.dtd">
<suite name="API test">
    <test name="Test Account Service">
        <classes>
            <class name="example.demo.apitests.TestAccountService"/>
        </classes>
    </test>
    <test name="Test Category Service">
        <classes>
            <class name="example.demo.apitests.TestCategoryService"/>
        </classes>
    </test>
    <test name="Test System Profile Service">
        <classes>
            <class name="example.demo.apitests.TestSystemProfileService"/>
        </classes>
    </test>
</suite>